vtk.py
vtkmodules/__init__.py
vtkmodules/all.py
vtkmodules/generate_pyi.py
vtkmodules/libvtkChartsCore-9.3.so
vtkmodules/libvtkCommonColor-9.3.so
vtkmodules/libvtkCommonComputationalGeometry-9.3.so
vtkmodules/libvtkCommonCore-9.3.so
vtkmodules/libvtkCommonDataModel-9.3.so
vtkmodules/libvtkCommonExecutionModel-9.3.so
vtkmodules/libvtkCommonMath-9.3.so
vtkmodules/libvtkCommonMisc-9.3.so
vtkmodules/libvtkCommonPython-9.3.so
vtkmodules/libvtkCommonSystem-9.3.so
vtkmodules/libvtkCommonTransforms-9.3.so
vtkmodules/libvtkDICOMParser-9.3.so
vtkmodules/libvtkDomainsChemistry-9.3.so
vtkmodules/libvtkDomainsChemistryOpenGL2-9.3.so
vtkmodules/libvtkFiltersAMR-9.3.so
vtkmodules/libvtkFiltersCellGrid-9.3.so
vtkmodules/libvtkFiltersCore-9.3.so
vtkmodules/libvtkFiltersExtraction-9.3.so
vtkmodules/libvtkFiltersFlowPaths-9.3.so
vtkmodules/libvtkFiltersGeneral-9.3.so
vtkmodules/libvtkFiltersGeneric-9.3.so
vtkmodules/libvtkFiltersGeometry-9.3.so
vtkmodules/libvtkFiltersGeometryPreview-9.3.so
vtkmodules/libvtkFiltersHybrid-9.3.so
vtkmodules/libvtkFiltersHyperTree-9.3.so
vtkmodules/libvtkFiltersImaging-9.3.so
vtkmodules/libvtkFiltersModeling-9.3.so
vtkmodules/libvtkFiltersParallel-9.3.so
vtkmodules/libvtkFiltersParallelImaging-9.3.so
vtkmodules/libvtkFiltersPoints-9.3.so
vtkmodules/libvtkFiltersProgrammable-9.3.so
vtkmodules/libvtkFiltersPython-9.3.so
vtkmodules/libvtkFiltersReduction-9.3.so
vtkmodules/libvtkFiltersSMP-9.3.so
vtkmodules/libvtkFiltersSelection-9.3.so
vtkmodules/libvtkFiltersSources-9.3.so
vtkmodules/libvtkFiltersStatistics-9.3.so
vtkmodules/libvtkFiltersTensor-9.3.so
vtkmodules/libvtkFiltersTexture-9.3.so
vtkmodules/libvtkFiltersTopology-9.3.so
vtkmodules/libvtkFiltersVerdict-9.3.so
vtkmodules/libvtkGeovisCore-9.3.so
vtkmodules/libvtkIOAMR-9.3.so
vtkmodules/libvtkIOAsynchronous-9.3.so
vtkmodules/libvtkIOCGNSReader-9.3.so
vtkmodules/libvtkIOCONVERGECFD-9.3.so
vtkmodules/libvtkIOCellGrid-9.3.so
vtkmodules/libvtkIOCesium3DTiles-9.3.so
vtkmodules/libvtkIOChemistry-9.3.so
cadquery_vtk-9.3.1.dist-info/LICENSE
cadquery_vtk-9.3.1.dist-info/METADATA
cadquery_vtk-9.3.1.dist-info/WHEEL
cadquery_vtk-9.3.1.dist-info/top_level.txt
cadquery_vtk-9.3.1.dist-info/RECORD
