Metadata-Version: 2.2
Name: cadquery_vtk
Version: 9.3.1
Summary: VTK is an open-source toolkit for 3D computer graphics, image processing, and visualization
Home-page: https://vtk.org
Download-URL: https://vtk.org/download/
Author: VTK developers
License: BSD
Classifier: License :: OSI Approved :: BSD License
Classifier: Programming Language :: Python
Classifier: Programming Language :: C++
Classifier: Intended Audience :: Developers
Classifier: Intended Audience :: Education
Classifier: Intended Audience :: Healthcare Industry
Classifier: Intended Audience :: Science/Research
Classifier: Topic :: Multimedia :: Graphics
Classifier: Topic :: Multimedia :: Graphics :: 3D Modeling
Classifier: Topic :: Multimedia :: Graphics :: 3D Rendering
Classifier: Topic :: Scientific/Engineering
Classifier: Topic :: Scientific/Engineering :: Chemistry
Classifier: Topic :: Scientific/Engineering :: Information Analysis
Classifier: Topic :: Scientific/Engineering :: Medical Science Apps.
Classifier: Topic :: Scientific/Engineering :: Physics
Classifier: Topic :: Scientific/Engineering :: Visualization
Classifier: Topic :: Software Development :: Libraries
Classifier: Operating System :: Microsoft :: Windows
Classifier: Operating System :: POSIX
Classifier: Operating System :: Unix
Classifier: Operating System :: MacOS
License-File: LICENSE
Provides-Extra: gtk
Provides-Extra: numpy
Requires-Dist: numpy>=1.9; extra == "numpy"
Provides-Extra: qt
Provides-Extra: tk
Provides-Extra: wx
Provides-Extra: rendering
Provides-Extra: rendering-onscreen-x11
Provides-Extra: rendering-onscreen
Provides-Extra: rendering-backend-gl
Dynamic: author
Dynamic: classifier
Dynamic: description
Dynamic: description-content-type
Dynamic: download-url
Dynamic: home-page
Dynamic: license
Dynamic: provides-extra
Dynamic: summary
